Workbook

Sheet Титульник
F1: Министерство образования Республики Беларусь
F2: Учреждение образования
F3: «Белорусский государственный университет информатики и радиоэлектроники»
F5: Факультет информационных технологий и управления
C6: Кафедра информационных технологий автоматизированных систем
F14: Лабораторная работа № 8
C16: РЕШЕНИЕ ЗАДАЧ ОПТИМИЗАЦИИ
C17: НА ОСНОВЕ МОДЕЛЕЙ МАССОВОГО ОБСЛУЖИВАНИЯ
B26: Проверил: | I26: Выполнил:
B27: Протченко Е.В. | I27: ст. гр. 320xxx
F36: Минск 2025

Sheet Лаба

Sheet Станок А
A1: Найти характеристики работы станка A
A3: На участке выпускаются детали двух видов. Интервалы времени между моментами поступления заготовок для выпуска деталей примерно постоянные и составляют 5 минут. Все заготовки обрабатываются на станке А; время обработки на станке составляет 4±2 минуты.
B7: A
A8: Работа | B8: 0.2
A9: Простой | B9: 0.1
A10: Прочие расходы, связанные с выпуском деталей, следующие: деталь типа 1 – 4 д.е., деталь типа 2 – 10 д.е. (включая расходы на выпуск детали типа 1). Детали типа 1 продаются по цене 8 д.е., типа 2 – 45 д.е.
A13: Параметры станка А
A14: Интенсивность потока заявок, дет/мин. | B14: 𝜆 = 1/5= | C14: =1/5 -> 0.2 | D14: (2+6)/2=4
A15: Количество каналов | B15: m = | C15: 1
A16: Среднее время обслуживания заявки | B16: x̅ = | C16: 4
A17: Интенвивность обсл. заявок, дет/мин. | B17: µ = 1/x̅ = | C17: =1/C16 -> 0.25
A19: Характеристики станка А
A20: Вероятность простоя, Ро | B20: 1 - ρ= | C20: =1-C30 -> 0.2
A21: Вероятность отказа, Ротк | C21: 0
A22: Вероятность обслуживания, Робсл | C22: 1
A23: Коэф.загрузки, U | B23: ρ = | C23: =C30 -> 0.8
A24: Средняя длина очереди, q̅ | B24: (ρ^2*(v^2+ε^2))/ (2*(1-ρ)) = | C24: =(C30^2*(C31^2+C32^2))/(2*(1-C30)) -> 0.4
A25: Среднее число занятых каналов, S̅ | B25: m*U= | C25: =C15*C23 -> 0.8
A26: На обслуживании в очереди, k̅ | B26: q̅ + S̅ = | C26: =C24+C25 -> 1.2
A27: Среднее время ожидания обслучивания, w̅ | B27: q̅ / γ = | C27: =C24/C29 -> 2
A28: В очереди и на обслуживании, t̅ | B28: w̅ + x̅ = | C28: =C27+C16 -> 6
A29: Пропускная способность, γ | B29: 𝜆 = | C29: =C14 -> 0.2
A30: Нагрузка на канал, ρ | B30: 𝜆 / (m*µ)= | C30: =C14/(C15*C17) -> 0.8
A31: Коэфф вариации интервалов времени между заявками, v | B31: σ/x̅ = | C31: 0 | D31: регулярный поток
A32: Коэфф вариации времени обслуживания, ε | C32: =2/4 -> 0.5 | D32: 4- среднее значение, 2- среднее отклонение
A35: Станок А загружен на 80 % своего времени, а в течение 20% своего времени простаивает из-за отсутствия заготовок. Такая загрузка находится в оптимальном диапазоне 0,75–0,85, значит, станок работает нормально. В среднем в очереди находится 0,4 заготовки, а на станке — 0,8 заготовки.Станок обрабатывает в среднем 0,2 заготовки/мин.

Sheet Станки В1-В2
A1: Найти характеристики работы группы станков B1-B2 (8.13, 8.4, 8.9). Поток деталей на эту группу станков считать пуассоновским.
A4: Детали типа 1 со станка A поступают на два одинаковых станка (B1 и B2);
A5: Время обработки одной детали на этих станках распределено по экспоненциальному закону и составляет в среднем 20 минут. Перед станками В1 и В2 установлен общий накопитель, вмещающий пять деталей.
A9: Параметры станков В1-В2
A10: Интенсивность потока заявок, дет/мин | B10: 𝜆 = 0,9*(1/5 )= | C10: =0.9*0.2 -> 0.18
A11: Количество каналов | B11: m = | C11: 2
A12: Среднее время обслуживания заявки | B12: x̅ = | C12: 20
A13: Интенвивность обсл. заявок, дет/мин | B13: µ = 1/x̅ = | C13: =1/C12 -> 0.05
A15: Характеристики станков В1-В2
A16: Вероятность простоя, Ро | C16: =((C11*C26)^0/FACT(0)+(C11*C26)^1/FACT(1)+(C11*C26)^2/FACT(2)+(C11*C26)^(C11+1)/(C11*FACT(C11))*(1-C26^5)/(1-C26))^(-1) -> 0.0036764839
A17: Вероятность отказа, Ротк | B17: (mρ)^(m+n)/(m^n⋅m!) *P0 = | C17: =( (C11*C26)^(C11+5) / (C11^5*FACT(C11)) ) * C16 -> 0.45016342
A18: Вероятность обслуживания, Робсл | B18: 1-Ротк= | C18: =1-C17 -> 0.54983658
A19: Коэф.загрузки, U | B19: ρ * (1-Ротк) = | C19: =C26*C18 -> 0.98970585
A20: Средняя длина очереди, q̅ | B20: ((mρ)^(m+1)∗P_0)/(m⋅m!)∗(1-(n+1) ρ^n+nρ^(n+1))/(1-ρ)^2 = | C20: =(((C26*2)^(2+1)*C16)/(2*2))*((1-6*C26^5+5*C26^6)/((1-C26)^2)) -> 3.8652578
A21: Среднее число занятых каналов, S̅ | B21: m*U= | C21: =C11*C19 -> 1.9794117
A22: На обслуживании в очереди, k̅ | B22: q̅ + S̅ = | C22: =C20+C21 -> 5.8446695
A23: Среднее время ожидания обслучивания, w̅ | B23: q̅ / γ = | C23: =C20/C25 -> 39.054612
A24: В очереди и на обслуживании, t̅ | B24: w̅ + x̅ = | C24: =C23+C12 -> 59.054612
A25: Пропускная способность, γ | B25: µ * S̅ = | C25: =C13*C21 -> 0.098970585
A26: Нагрузка на канал, ρ | B26: 𝜆 / (m*µ)= | C26: =C10/(C11*C13) -> 1.8 | D26: >1
A27: 5.Вероятность отсутствия очереди, Р(j≤1) | B27: P0+P(1)=P0+(mρ)^(m−1)/((m−1)!) P0 = | C27: =C16+(C11*C26)*C16 -> 0.016911826
A30: Станки B1 и B2 загружены на 99 % своего времени, а в течение 1% своего времени простаивает из-за отсутствия заготовок. Такую закрузку нельзя считать нормальной, поэтому необходимо уменьшить нагрузку (оптимальный коэффициент загрузки = 0,75 - 0,85). В среднем в очереди находится 1,136 заготовки, а на станке - 3,8653 заготовки. Станок обрабатывает в среднем 0,099 заготовок/мин.

Sheet Станок С
A1: Перед станками В1 и В2 установлен общий накопитель, вмещающий пять деталей; при его заполнении все поступающие детали типа 1 направляются на станок С, на котором обработка занимает в среднем 6 минут (экспоненциальная случайная величина).
A6: Параметры станков C
A7: Интенсивность потока заявок, дет/мин | B7: P𝜆 = | C7: ='Станки В1-В2'!C10*'Станки В1-В2'!C17 -> 0.081029415
A8: Количество каналов | B8: m = | C8: 1
A9: Среднее время обслуживания заявки | B9: x̅ = | C9: 6
A10: Интенвивность обсл. заявок, дет/мин | B10: µ = 1/x̅ = | C10: =1/C9 -> 0.16666667
A12: Характеристики станков C
A13: Вероятность простоя, Ро | B13: 1 - ρ = | C13: =1-C23 -> 0.51382351
A14: Вероятность отказа, Ротк | C14: 0
A15: Вероятность обслуживания, Робсл | B15: 1-Ротк= | C15: =1-C14 -> 1
A16: Коэф.загрузки, U | B16: ρ = | C16: =C23*C15 -> 0.48617649
A17: Средняя длина очереди, q̅ | B17: (ρ^2*(v^2+ε^2))/ (2*(1-ρ))= | C17: =(C23^2*(C24^2+C25^2))/(2*(1-C23)) -> 0.46001707
A18: Среднее число занятых каналов, S̅ | B18: m*U= | C18: =C8*C16 -> 0.48617649
A19: На обслуживании в очереди, k̅ | B19: q̅ + S̅ = | C19: =C17+C18 -> 0.94619356
A20: Среднее время ожидания обслучивания, w̅ | B20: q̅ / γ = | C20: =C17/C22 -> 5.6771614
A21: В очереди и на обслуживании, t̅ | B21: w̅ + x̅ = | C21: =C20+C9 -> 11.677161
A22: Пропускная способность, γ | B22: 𝜆 = | C22: =C7 -> 0.081029415
A23: Нагрузка на канал, ρ | B23: 𝜆 / (m*µ)= | C23: =C7/(C8*C10) -> 0.48617649 | D23: <1
A24: Коэфф вариации интервалов времени между заявками, v | C24: 1 | D24: экспоненциальный
A25: Коэфф вариации времени обслуживания, ε | C25: 1 | D25: экспоненциальный
A27: Станок С загружен на 49 % своего времени, а в течение 51% своего времени простаивает из-за отсутствия заготовок. Такую закрузку нельзя считать нормальной, поэтому необходимо увеличить нагрузку (оптимальный коэффициент загрузки = 0,75 - 0,85)._x000B_В среднем в очереди находится 0,46 заготовки(q), а на станке - 0,4862 заготовки( S̅ ). Станок обрабатывает в среднем 0,081 заготовок/мин.

Sheet Прибыль8ч
A1: Найти прибыль от работы участка за 8 часов (8.6, 8.7, 8.9)
A2: Выручка от обслуживания заявок в течении времени Т:
A3: V = γ*C*T=V(A)+V(B1-B2)+V(C)= | E3: =B14*B15*480+C14*C15*480+D14*D15*480 -> 4656
A4: Затраты связанные собслуживанием заявок в канале в в течение времени Т:
A5: Zобсл = γ* Cобсл* T= | E5: =B14*B16*480+C14*C16*480+D14*D16*480 -> 1248
A6: Затраты, связанные с эксплуатацией канала в течение времени T:
A7: Zэксп = ( S̅ * Cраб + (m - S̅ ) *Cпр )*T= | E7: =(B18*B10+(B19-B18)*B11)*B17+(C18*C10+(C19-C18)*C11)*B17+(D18*D10+(D19-D18)*D11)*B17 -> 583.77882
B9: A | C9: B | D9: C
A10: Работа | B10: 0.2 | C10: 0.3 | D10: 0.8
A11: Простой | B11: 0.1 | C11: 0.1 | D11: 0.1
A12: Прочие расходы, связанные с выпуском деталей, следующие: деталь типа 1 – 4 д.е., деталь типа 2 – 10 д.е. (включая расходы на выпуск детали типа 1). Детали типа 1 продаются по цене 8 д.е., типа 2 – 45 д.е.
A14: γ | B14: ='Станок А'!$C$29 -> 0.2 | C14: ='Станки В1-В2'!$C$25 -> 0.098970585 | D14: ='Станок С'!C22 -> 0.081029415
A15: Выручка | B15: 8 | C15: 45 | D15: 45
A16: Прочие | B16: 4 | C16: 10 | D16: 10
A17: Т, мин | B17: 480
A18: S̅ | B18: ='Станок А'!$C$25 -> 0.8 | C18: ='Станки В1-В2'!$C$21 -> 1.9794117 | D18: ='Станок С'!C18 -> 0.48617649
A19: m | B19: 1 | C19: 2 | D19: 1
A21: Общая прибль: | C21: V - Zобсл - Zэксп = | E21: =E3-E5-E7 -> 2824.2212

Sheet Новое условие А
A1: Заготовки поступают на обработку чаще (в среднем через каждые 4 минуты), а станок А заменен на новый (А1); время обработки одной детали на станке А1 – 3±1 минута.
B5: A1
A6: Работа | B6: 0.4
A7: Простой | B7: 0.2
A11: Параметры станка А
A12: Интенсивность потока заявок, дет/мин. | B12: 𝜆 = 1/4 = | C12: =1/4 -> 0.25 | D12: (2+4)/2=3
A13: Количество каналов | B13: m = | C13: 1
A14: Среднее время обслуживания заявки | B14: x̅ = | C14: 3
A15: Интенвивность обсл. заявок, дет/мин. | B15: µ = 1/x̅ = | C15: =1/C14 -> 0.33333333
A17: Характеристики станка А
A18: Вероятность простоя, Ро | B18: 1 - ρ= | C18: =1-C28 -> 0.25
A19: Вероятность отказа, Ротк | C19: 0
A20: Вероятность обслуживания, Робсл | C20: 1
A21: Коэф.загрузки, U | B21: ρ = | C21: =C28 -> 0.75
A22: Средняя длина очереди, q̅ | B22: (ρ^2*(v^2+ε^2))/ (2*(1-ρ)) = | C22: =(C28^2*(C29^2+C30^2))/(2*(1-C28)) -> 1.25
A23: Среднее число занятый каналов, S̅ | B23: m*U= | C23: =C13*C21 -> 0.75
A24: На обслуживании в очереди, k̅ | B24: q̅ + S̅ = | C24: =C22+C23 -> 2
A25: Среднее время ожидания обслучивания, w̅ | B25: q̅ / γ = | C25: =C22/C27 -> 5
A26: В очереди и на обслуживании, t̅ | B26: w̅ + x̅ = | C26: =C25+C14 -> 8
A27: Пропускная способность, γ | B27: 𝜆 = | C27: =C12 -> 0.25
A28: Нагрузка на канал, ρ | B28: 𝜆 / (m*µ)= | C28: =C12/(C13*C15) -> 0.75
A29: Коэфф вариации интервалов времени между заявками, v | B29: σ/x̅ = | C29: 1 | D29: экспоненциальный
A30: Коэфф вариации времени обслуживания, ε | C30: =1/3 -> 0.33333333 | D30: 3 - среднее, 1 - среднее отклонение
A33: Станок А загружен на 75 % своего времени, а в течение 25% своего времени простаивает из-за отсутствия заготовок. Такая загрузка находится в оптимальном диапазоне 0,75–0,85, значит, станок работает нормально.В среднем в очереди находится 1,25 заготовки, а на станке - 0,75 заготовки. Станок обрабатывает в среднем 0,25 заготовок/мин.

Sheet Новое условие В
A1: Найти характеристики работы группы станков B1-B2 (8.13, 8.4, 8.9). Поток деталей на эту группу станков считать пуассоновским.
A4: Детали типа 1 со станка A поступают на два одинаковых станка (B1 и B2);
A5: Время обработки одной детали на этих станках распределено по экспоненциальному закону и составляет в среднем 20 минут. Перед станками В1 и В2 установлен общий накопитель, вмещающий пять деталей.
A9: Параметры станков В1-В2
A10: Интенсивность потока заявок, дет/мин | B10: 𝜆 = 0,9*(1/4 )= | C10: =0.9*0.25 -> 0.225
A11: Количество каналов | B11: m = | C11: 2
A12: Среднее время обслуживания заявки | B12: x̅ = | C12: 20
A13: Интенвивность обсл. заявок, дет/мин | B13: µ = 1/x̅ = | C13: =1/C12 -> 0.05
A15: Характеристики станков В1-В2
A16: Вероятность простоя, Ро | C16: =((C11*C26)^0/FACT(0)+(C11*C26)^1/FACT(1)+(C11*C26)^2/FACT(2)+(C11*C26)^(C11+1)/(C11*FACT(C11))*(1-C26^5)/(1-C26))^(-1) -> 0.00095388415
A17: Вероятность отказа, Ротк | B17: (mρ)^(m+n)/(m^n⋅m!) *P0 = | C17: =((C11*C26)^7/(2^5*2))*C16 -> 0.55693339
A18: Вероятность обслуживания, Робсл | B18: 1-Ротк= | C18: =1-C17 -> 0.44306661
A19: Коэф.загрузки, U | B19: ρ * (1-Ротк) = | C19: =C26*C18 -> 0.99689988
A20: Средняя длина очереди, q̅ | B20: ((mρ)^(m+1)∗P_0)/(m⋅m!)∗(1-(n+1) ρ^n+nρ^(n+1))/(1-ρ)^2 = | C20: =(((C26*2)^(2+1)*C16)/(2*2))*((1-6*C26^5+5*C26^6)/((1-C26)^2)) -> 4.224324
A21: Среднее число занятых каналов, S̅ | B21: m*U= | C21: =C11*C19 -> 1.9937998
A22: На обслуживании в очереди, k̅ | B22: q̅ + S̅ = | C22: =C20+C21 -> 6.2181238
A23: Среднее время ожидания обслучивания, w̅ | B23: q̅ / γ = | C23: =C20/C25 -> 42.374607
A24: В очереди и на обслуживании, t̅ | B24: w̅ + x̅ = | C24: =C23+C12 -> 62.374607
A25: Пропускная способность, γ | B25: µ * S̅ = | C25: =C13*C21 -> 0.099689988
A26: Нагрузка на канал, ρ | B26: 𝜆 / (m*µ)= | C26: =C10/(C11*C13) -> 2.25 | D26: >1
A27: 5.Вероятность отсутствия очереди, Р(j≤1) | B27: P0+P(1)=P0+(mρ)^(m−1)/((m−1)!) P0 = | C27: =C16+(C11*C26)*C16 -> 0.0052463628
A30: Станки B1 и B2 загружены на 99 % своего времени, а в течение 1% своего времени простаивает из-за отсутствия заготовок. Такую закрузку нельзя считать нормальной, поэтому необходимо уменьшить нагрузку (оптимальный коэффициент загрузки = 0,75 - 0,85). В среднем в очереди находится 4,224 заготовки, а на станке - 1,994 заготовки. Станок обрабатывает в среднем 0,0997 заготовок/мин.

Sheet Новое условие С
A1: Перед станками В1 и В2 установлен общий накопитель, вмещающий пять деталей; при его заполнении все поступающие детали типа 1 направляются на станок С, на котором обработка занимает в среднем 6 минут (экспоненциальная случайная величина).
A6: Параметры станков C
A7: Интенсивность потока заявок, дет/мин | B7: P𝜆 = | C7: ='Новое условие В'!C10*'Новое условие В'!C17 -> 0.12531001
A8: Количество каналов | B8: m = | C8: 1
A9: Среднее время обслуживания заявки | B9: x̅ = | C9: 6
A10: Интенвивность обсл. заявок, дет/мин | B10: µ = 1/x̅ = | C10: =1/C9 -> 0.16666667
A12: Характеристики станков C
A13: Вероятность простоя, Ро | B13: 1 - ρ = | C13: =1-C23 -> 0.24813993
A14: Вероятность отказа, Ротк | C14: 0
A15: Вероятность обслуживания, Робсл | B15: 1-Ротк= | C15: =1-C14 -> 1
A16: Коэф.загрузки, U | B16: ρ = | C16: =C23*C15 -> 0.75186007
A17: Средняя длина очереди, q̅ | B17: (ρ^2*(v^2+ε^2))/ (2*(1-ρ))= | C17: =(C23^2*(C24^2+C25^2))/(2*(1-C23)) -> 2.2781242
A18: Среднее число занятых каналов, S̅ | B18: m*U= | C18: =C8*C16 -> 0.75186007
A19: На обслуживании в очереди, k̅ | B19: q̅ + S̅ = | C19: =C17+C18 -> 3.0299843
A20: Среднее время ожидания обслучивания, w̅ | B20: q̅ / γ = | C20: =C17/C22 -> 18.179906
A21: В очереди и на обслуживании, t̅ | B21: w̅ + x̅ = | C21: =C20+C9 -> 24.179906
A22: Пропускная способность, γ | B22: 𝜆 = | C22: =C7 -> 0.12531001
A23: Нагрузка на канал, ρ | B23: 𝜆 / (m*µ)= | C23: =C7/(C8*C10) -> 0.75186007
A24: Коэфф вариации интервалов времени между заявками, v | C24: 1
A25: Коэфф вариации времени обслуживания, ε | C25: 1
A28: Станок С загружен на 75 % своего времени, а в течение 25% своего времени простаивает из-за отсутствия заготовок. Такая загрузка находится в оптимальном диапазоне 0,75–0,85, значит, станок работает нормально. В среднем в очереди находится 2,28 заготовки, а на станке - 0,75 заготовки. Станок обрабатывает в среднем 0,1253 заготовок/мин.

Sheet Новая_Прибыль
A1: Найти прибыль от работы участка за 8 часов (8.6, 8.7, 8.9)
A3: Выручка от обслуживания заявок в течении времени Т:
A4: V = γ*C*T=V(A)+V(B1-B2)+V(C)= | E4: =B15*B16*480+C15*C16*480+D15*D16*480 -> 5820
A5: Затраты связанные собслуживанием заявок в канале в в течение времени Т:
A6: Zобсл = γ* Cобсл* T= | E6: =B15*B17*480+C15*C17*480+D15*D17*480 -> 1560
A7: Затраты, связанные с эксплуатацией канала в течение времени T:
A8: Zэксп = ( S̅ * Cраб + (m - S̅ ) *Cпр )*T= | E8: =(B19*B11+(B20-B19)*B12)*B18+(C19*C11+(C20-C19)*C12)*B18+(D19*D11+(D20-D19)*D12)*B18 -> 756.02976
B10: A | C10: B | D10: C
A11: Работа | B11: 0.4 | C11: 0.3 | D11: 0.8
A12: Простой | B12: 0.2 | C12: 0.1 | D12: 0.1
A13: Прочие расходы, связанные с выпуском деталей типа 1 и 2, составляют 2 и 8 д.е. соответственно. Детали типа 1 продаются по цене 5 д.е., типа 2 - 22 д.е.
A15: γ | B15: ='Новое условие А'!C27 -> 0.25 | C15: ='Новое условие В'!C25 -> 0.099689988 | D15: ='Новое условие С'!C22 -> 0.12531001
A16: Выручка | B16: 8 | C16: 45 | D16: 45
A17: Прочие расх. | B17: 4 | C17: 10 | D17: 10
A18: Т, мин | B18: 480
A19: S̅ | B19: ='Новое условие А'!C21 -> 0.75 | C19: ='Новое условие В'!C21 -> 1.9937998 | D19: ='Новое условие С'!C18 -> 0.75186007
A20: m | B20: 1 | C20: 2 | D20: 1
A22: Общая прибль: | C22: V - Zобсл - Zэксп = | E22: =E4-E6-E8 -> 3503.9702

Sheet Сравнение
A1: Характеристики | C1: А | D1: В1-В2 | E1: С | F1: А1 | G1: В1"-В2" | H1: С"
A2: P0 | C2: ='Станок А'!C20 -> 0.2 | D2: ='Станки В1-В2'!C16 -> 0.0036764839 | E2: ='Станок С'!C13 -> 0.51382351 | F2: ='Новое условие А'!C18 -> 0.25 | G2: ='Новое условие В'!C16 -> 0.00095388415 | H2: ='Новое условие С'!C13 -> 0.24813993
A3: Pотк | C3: ='Станок А'!C21 -> 0 | D3: ='Станки В1-В2'!C17 -> 0.45016342 | E3: ='Станок С'!C14 -> 0 | F3: ='Новое условие А'!C19 -> 0 | G3: ='Новое условие В'!C17 -> 0.55693339 | H3: ='Новое условие С'!C14 -> 0
A4: Pобсл | C4: ='Станок А'!C22 -> 1 | D4: ='Станки В1-В2'!C18 -> 0.54983658 | E4: ='Станок С'!C15 -> 1 | F4: ='Новое условие А'!C20 -> 1 | G4: ='Новое условие В'!C18 -> 0.44306661 | H4: ='Новое условие С'!C15 -> 1
A5: ρ | C5: ='Станок А'!C30 -> 0.8 | D5: ='Станки В1-В2'!C26 -> 1.8 | E5: ='Станок С'!C23 -> 0.48617649 | F5: ='Новое условие А'!C28 -> 0.75 | G5: ='Новое условие В'!C26 -> 2.25 | H5: ='Новое условие С'!C23 -> 0.75186007
A6: U | C6: ='Станок А'!C23 -> 0.8 | D6: ='Станки В1-В2'!C19 -> 0.98970585 | E6: ='Станок С'!C16 -> 0.48617649 | F6: ='Новое условие А'!C21 -> 0.75 | G6: ='Новое условие В'!C19 -> 0.99689988 | H6: ='Новое условие С'!C18 -> 0.75186007
A7: S̅ , деталей | C7: ='Станок А'!C25 -> 0.8 | D7: ='Станки В1-В2'!C21 -> 1.9794117 | E7: ='Станок С'!C18 -> 0.48617649 | F7: ='Новое условие А'!C23 -> 0.75 | G7: ='Новое условие В'!C21 -> 1.9937998 | H7: ='Новое условие С'!C18 -> 0.75186007
A8: 𝑞̅ , деталей | C8: ='Станок А'!C24 -> 0.4 | D8: ='Станки В1-В2'!C20 -> 3.8652578 | E8: ='Станок С'!C17 -> 0.46001707 | F8: ='Новое условие А'!C22 -> 1.25 | G8: ='Новое условие В'!C20 -> 4.224324 | H8: ='Новое условие С'!C17 -> 2.2781242
A9: k, деталей | C9: ='Станок А'!C26 -> 1.2 | D9: ='Станки В1-В2'!C22 -> 5.8446695 | E9: ='Станок С'!C19 -> 0.94619356 | F9: ='Новое условие А'!C24 -> 2 | G9: ='Новое условие В'!C22 -> 6.2181238 | H9: ='Новое условие С'!C23 -> 0.75186007
A10: 𝛾, дет/мин | C10: ='Станок А'!C29 -> 0.2 | D10: ='Станки В1-В2'!C25 -> 0.098970585 | E10: ='Станок С'!C22 -> 0.081029415 | F10: ='Новое условие А'!C27 -> 0.25 | G10: ='Новое условие В'!C25 -> 0.099689988 | H10: ='Новое условие С'!C22 -> 0.12531001
A11: 𝑤̅, мин | C11: ='Станок А'!C27 -> 2 | D11: ='Станки В1-В2'!C23 -> 39.054612 | E11: ='Станок С'!C20 -> 5.6771614 | F11: ='Новое условие А'!C25 -> 5 | G11: ='Новое условие В'!C23 -> 42.374607 | H11: ='Новое условие С'!C20 -> 18.179906
A12: 𝑡̅, мин | C12: ='Станок А'!C28 -> 6 | D12: ='Станки В1-В2'!C24 -> 59.054612 | E12: ='Станок С'!C21 -> 11.677161 | F12: ='Новое условие А'!C26 -> 8 | G12: ='Новое условие В'!C24 -> 62.374607 | H12: ='Новое условие С'!C21 -> 24.179906
A13: Вероятность отсутствия очереди B1-B2 | C13: ='Станки В1-В2'!C27 -> 0.016911826 | F13: ='Новое условие В'!C27 -> 0.0052463628
A14: Прибыль | C14: =Прибыль8ч!E21 -> 2824.2212 | F14: =Новая_Прибыль!E22 -> 3503.9702 | I14: Прибыль увеличилась на 24%
